tomato_example_counter/__init__.py
tomato_example_counter-2.1.1.dist-info/licenses/LICENSE
tomato_example_counter-2.1.1.dist-info/METADATA
tomato_example_counter-2.1.1.dist-info/WHEEL
tomato_example_counter-2.1.1.dist-info/top_level.txt
tomato_example_counter-2.1.1.dist-info/RECORD
