Metadata-Version: 2.4
Name: tomato-example-counter
Version: 2.1.1
Summary: tomato example counter driver
Author-email: Peter Kraus <peter.kraus@tu-berlin.de>
Maintainer-email: Peter Kraus <peter.kraus@tu-berlin.de>
Project-URL: Documentation, https://dgbowl.github.io/tomato-example-counter/main
Project-URL: Issues, https://github.com/dgbowl/tomato-example-counter/issues
Project-URL: Repository, https://github.com/dgbowl/tomato-example-counter/
Classifier: Development Status :: 4 - Beta
Classifier: License :: OSI Approved :: GNU General Public License v3 or later (GPLv3+)
Classifier: Programming Language :: Python :: 3.10
Classifier: Programming Language :: Python :: 3.13
Classifier: Operating System :: OS Independent
Requires-Python: >=3.10
License-File: LICENSE
Requires-Dist: tomato>=2.1rc3
Provides-Extra: testing
Requires-Dist: pytest; extra == "testing"
Dynamic: license-file
